context_menu/__init__.py
context_menu/linux_menus.py
context_menu/menus.py
context_menu/pytest_plugin.py
context_menu/windows_menus.py
context_menu-1.4.1.dist-info/LICENSE
context_menu-1.4.1.dist-info/METADATA
context_menu-1.4.1.dist-info/WHEEL
context_menu-1.4.1.dist-info/top_level.txt
context_menu-1.4.1.dist-info/RECORD
