Metadata-Version: 2.1
Name: context-menu
Version: 1.4.1
Summary: Library to create cross-platform native context menus.
Home-page: https://github.com/saleguas/context_menu
Author: Salvador Aleguas
Author-email: salvador@aleguas.dev
License: MIT
Classifier: License :: OSI Approved :: MIT License
Classifier: Programming Language :: Python :: 3.7
Classifier: Programming Language :: Python :: 3.8
Classifier: Programming Language :: Python :: 3.9
Requires-Python: >= 3.7
License-File: LICENSE
Provides-Extra: test
Requires-Dist: pytest-html ; extra == 'test'
